mongo_thingy/__init__.py
mongo_thingy/camelcase.py
mongo_thingy/cursor.py
mongo_thingy/versioned.py
Mongo_Thingy-0.17.2.dist-info/LICENSE
Mongo_Thingy-0.17.2.dist-info/METADATA
Mongo_Thingy-0.17.2.dist-info/WHEEL
Mongo_Thingy-0.17.2.dist-info/top_level.txt
Mongo_Thingy-0.17.2.dist-info/RECORD
