Metadata-Version: 2.1
Name: Mongo-Thingy
Version: 0.17.2
Summary: The most idiomatic and friendly-yet-powerful way to use MongoDB with Python
Home-page: https://github.com/Refty/mongo-thingy
Author: Guillaume Gelin
Author-email: guillaume@refty.co
License: MIT
Platform: any
Classifier: Programming Language :: Python :: 3.7
Classifier: Programming Language :: Python :: 3.8
Classifier: Programming Language :: Python :: 3.9
Classifier: Programming Language :: Python :: 3.10
Classifier: Programming Language :: Python :: 3.11
Classifier: Programming Language :: Python :: Implementation :: CPython
Classifier: Programming Language :: Python :: Implementation :: PyPy
Classifier: Intended Audience :: Developers
Classifier: Operating System :: OS Independent
Classifier: Programming Language :: Python
Classifier: Topic :: Database
Classifier: Topic :: Software Development :: Libraries :: Python Modules
License-File: LICENSE
Requires-Dist: thingy (>=0.10.0)
Requires-Dist: pymongo (>=4.6.3)
